dateconvert/__init__.py
dateconvert/constants.json
dateconvert/main.py
date_convert_ad_bs-1.1.4.dist-info/METADATA
date_convert_ad_bs-1.1.4.dist-info/WHEEL
date_convert_ad_bs-1.1.4.dist-info/top_level.txt
date_convert_ad_bs-1.1.4.dist-info/RECORD
