Metadata-Version: 2.1
Name: date-convert-ad-bs
Version: 1.1.4
Summary: Convert AD to BS and vice versa
Home-page: https://github.com/Ulleri-Tech/date-convert-AD-BS
Author: Ulleri Tech (Binij Shrestha)
Author-email: <uller@ulleri.tech>
License: MIT
Keywords: python,Convert Date,AD to BS,BS to AD
Classifier: Development Status :: 3 - Alpha
Classifier: Intended Audience :: Developers
Classifier: Programming Language :: Python :: 3
Classifier: Operating System :: Unix
Classifier: Operating System :: MacOS :: MacOS X
Classifier: Operating System :: Microsoft :: Windows
